{"cameraMode":{"drawMode":0,"name":"Shaded","section":"Shading Mode"},"sceneLighting":true,"audioPlay":false,"sceneViewState":{"m_AlwaysRefresh":false,"showFog":true,"showSkybox":true,"showFlares":true,"showImageEffects":true,"showParticleSystems":true,"showVisualEffectGraphs":true,"m_FxEnabled":true},"in2DMode":false,"pivot":{"x":-4.928323745727539,"y":0.9213168621063232,"z":-0.5242722630500794},"rotation":{"x":-0.08705630153417587,"y":-0.5573219656944275,"z":0.05890914052724838,"w":-0.8236108422279358},"size":0.8660253882408142,"orthographic":false}