{"cameraMode":{"drawMode":0,"name":"Shaded","section":"Shading Mode"},"sceneLighting":true,"audioPlay":false,"sceneViewState":{"m_AlwaysRefresh":false,"showFog":true,"showSkybox":true,"showFlares":true,"showImageEffects":true,"showParticleSystems":true,"showVisualEffectGraphs":true,"m_FxEnabled":true},"in2DMode":false,"pivot":{"x":-23.36002540588379,"y":6.965357303619385,"z":29.357751846313478},"rotation":{"x":-0.17751045525074006,"y":0.6065638661384583,"z":-0.14032258093357087,"w":-0.7617937326431274},"size":43.70589828491211,"orthographic":false}